{
  "metadata": {
    "name": "intelliqx",
    "root_path": "/Users/sachin/repo/intelliqx",
    "languages": [
      "python"
    ],
    "frameworks": [
      "django"
    ],
    "build_systems": [
      "make",
      "python",
      "docker"
    ],
    "architecture_style": "unknown",
    "total_files": 301,
    "total_lines": 38676,
    "analyzed_at": "2026-07-15T18:31:46.972098Z",
    "extra": {}
  },
  "parsed_entity_count": 2858,
  "layer_node_counts": {
    "call": 1634,
    "data_flow": 1308,
    "control_flow": 1634,
    "dependency": 586,
    "state_transition": 378,
    "resource": 1308,
    "security": 1634,
    "deployment": 70
  },
  "graph_node_total": 8552,
  "generated_files": 583,
  "optimization_summary": {
    "target_language": "python",
    "nodes_before": 8552,
    "nodes_after": 0,
    "edges_before": 3296,
    "edges_after": 0,
    "node_reduction": 8552,
    "edge_reduction": 3296,
    "pass_count": 4,
    "all_behavior_preserved": true,
    "max_risk_level": "medium",
    "duplicate_pairs_found": 0,
    "parallel_branches_found": 10
  },
  "duplicate_pairs": 0,
  "parallel_branches": 10,
  "auditors": {
    "underscore": 0,
    "unused_imports": 0,
    "long_functions": 63,
    "bare_except": 0,
    "silent_except_pass": 0,
    "missing_all": 0,
    "print_leaks": 10,
    "todo_fixme": 0,
    "id_based_caches": 0,
    "missing_docstrings": 55
  },
  "auto_fixes": {
    "underscore": {
      "findings": 0,
      "files_touched": 0,
      "applied": false
    },
    "unused_imports": {
      "removed": 0,
      "files_touched": 0,
      "skipped": [],
      "applied": false
    },
    "add_all": {
      "added": 0,
      "files_touched": 0,
      "applied": false
    }
  },
  "errors": [],
  "warnings": [],
  "ruff_clean": true,
  "tests_pass": true,
  "mode": "DRY-RUN"
}